WaterOptim/__init__.py
WaterOptim/__main__.py
WaterOptim/__version__.py
WaterOptim/config.json
WaterOptim/css.css
WaterOptim/dict.json
WaterOptim/enc__.enc
WaterOptim/html_template.html
WaterOptim/inf.enc
WaterOptim/uiwpinch.py
WaterOptim/wpinch.py
WaterOptim/__pycache__/__init__.cpython-38.pyc
WaterOptim/__pycache__/__init__.cpython-39.pyc
WaterOptim/__pycache__/__main__.cpython-39.pyc
WaterOptim/__pycache__/__version__.cpython-38.pyc
WaterOptim/__pycache__/__version__.cpython-39.pyc
WaterOptim/__pycache__/test_interdictions.cpython-39.pyc
WaterOptim/__pycache__/uiwpinch.cpython-38.pyc
WaterOptim/__pycache__/uiwpinch.cpython-39.pyc
WaterOptim/__pycache__/untitled2.cpython-39.pyc
WaterOptim/__pycache__/wpinch.cpython-38.pyc
WaterOptim/__pycache__/wpinch.cpython-39.pyc
WaterOptim/__pycache__/wpinch_batch.cpython-39.pyc
WaterOptim/design/__design__.py
WaterOptim/design/__design_source__.py
WaterOptim/design/__design_sources__.py
WaterOptim/design/__pycache__/__design__.cpython-38.pyc
WaterOptim/design/__pycache__/__design__.cpython-39.pyc
WaterOptim/design/__pycache__/__design_source__.cpython-38.pyc
WaterOptim/design/__pycache__/__design_source__.cpython-39.pyc
WaterOptim/design/__pycache__/__design_sources__.cpython-38.pyc
WaterOptim/design/__pycache__/__design_sources__.cpython-39.pyc
WaterOptim/icons/icon2json.py
WaterOptim/icons/icons.json
WaterOptim/icons/__pycache__/icon2json.cpython-38.pyc
WaterOptim/icons/__pycache__/icon2json.cpython-39.pyc
WaterOptim/inventories/__obj__.py
WaterOptim/inventories/__post__.py
WaterOptim/inventories/__regen__.py
WaterOptim/inventories/__sink__.py
WaterOptim/inventories/__source__.py
WaterOptim/inventories/__pycache__/__obj__.cpython-38.pyc
WaterOptim/inventories/__pycache__/__obj__.cpython-39.pyc
WaterOptim/inventories/__pycache__/__post__.cpython-38.pyc
WaterOptim/inventories/__pycache__/__post__.cpython-39.pyc
WaterOptim/inventories/__pycache__/__regen__.cpython-38.pyc
WaterOptim-1.6.9.dist-info/LICENSE.txt
WaterOptim-1.6.9.dist-info/METADATA
WaterOptim-1.6.9.dist-info/WHEEL
WaterOptim-1.6.9.dist-info/top_level.txt
WaterOptim-1.6.9.dist-info/RECORD
