Metadata-Version: 2.1
Name: WaterOptim
Version: 1.6.9
Summary: water pinch tool
Home-page: https://wateroptim.readthedocs.io/en/latest/
Author: Hedi ROMDHANA
Author-email: hedi.romdhana@agroparistech.fr
License: GPLv3
Keywords: water,pinch,process,integration
Classifier: Development Status :: 3 - Alpha
Classifier: Intended Audience :: Developers
Classifier: Programming Language :: Python :: 3.4
Classifier: Programming Language :: Python :: 3.5
Classifier: Programming Language :: Python :: 3.6
Classifier: Topic :: Software Development :: Testing
Classifier: License :: OSI Approved :: GNU General Public License v3 (GPLv3)
Requires-Python: >=3.4
License-File: LICENSE.txt
Requires-Dist: SALib
Requires-Dist: graphviz
Requires-Dist: prettytable
Requires-Dist: pydot
Requires-Dist: pyparsing
Requires-Dist: wxPython
Requires-Dist: tabulate
